GoZhongwenWendang/README.md
GoZhongwenWendang/__init__.py
GoZhongwenWendang/__main__.py
GoZhongwenWendang/file.epub
GoZhongwenWendang/index.html
GoZhongwenWendang/css/__init__.py
GoZhongwenWendang/css/annotations.css
GoZhongwenWendang/css/main.css
GoZhongwenWendang/css/normalize.css
GoZhongwenWendang/css/popup.css
GoZhongwenWendang/font/__init__.py
GoZhongwenWendang/font/fontello.eot
GoZhongwenWendang/font/fontello.svg
GoZhongwenWendang/font/fontello.ttf
GoZhongwenWendang/font/fontello.woff
GoZhongwenWendang/img/__init__.py
GoZhongwenWendang/img/annotator-glyph-sprite.png
GoZhongwenWendang/img/annotator-icon-sprite.png
GoZhongwenWendang/img/apple-touch-icon.png
GoZhongwenWendang/img/cancelfullscreen.png
GoZhongwenWendang/img/close.png
GoZhongwenWendang/img/fullscreen.png
GoZhongwenWendang/img/loader.gif
GoZhongwenWendang/img/menu-icon.png
GoZhongwenWendang/img/save.png
GoZhongwenWendang/img/saved.png
GoZhongwenWendang/img/settings-s.png
GoZhongwenWendang/img/settings.png
GoZhongwenWendang/img/star.png
GoZhongwenWendang/js/__init__.py
GoZhongwenWendang/js/epub.js
GoZhongwenWendang/js/epub.min.js
GoZhongwenWendang/js/epub.min.map
GoZhongwenWendang/js/hooks.min.js
GoZhongwenWendang/js/hooks.min.map
GoZhongwenWendang/js/reader.js
GoZhongwenWendang/js/reader.js.map
GoZhongwenWendang/js/reader.min.js
GoZhongwenWendang/js/reader.min.map
GoZhongwenWendang/js/hooks/__init__.py
GoZhongwenWendang/js/hooks/extensions/__init__.py
GoZhongwenWendang/js/hooks/extensions/highlight.js
GoZhongwenWendang/js/libs/__init__.py
GoZhongwenWendang/js/libs/jquery.min.js
GoZhongwenWendang/js/libs/localforage.min.js
GoZhongwenWendang/js/libs/screenfull.js
GoZhongwenWendang/js/libs/screenfull.min.js
GoZhongwenWendang/js/libs/zip.min.js
GoZhongwenWendang/js/plugins/__init__.py
GoZhongwenWendang/js/plugins/hypothesis.js
GoZhongwenWendang/js/plugins/search.js
go_zhongwen_wendang-2024.3.1.0.dist-info/METADATA
go_zhongwen_wendang-2024.3.1.0.dist-info/WHEEL
go_zhongwen_wendang-2024.3.1.0.dist-info/entry_points.txt
go_zhongwen_wendang-2024.3.1.0.dist-info/top_level.txt
go_zhongwen_wendang-2024.3.1.0.dist-info/RECORD
